phys_torch/__init__.py
phys_torch-0.1.3.dist-info/METADATA
phys_torch-0.1.3.dist-info/WHEEL
phys_torch-0.1.3.dist-info/licenses/LICENSE
phys_torch-0.1.3.dist-info/RECORD
