Metadata-Version: 2.4
Name: phys-torch
Version: 0.1.3
Summary: Vector Calculus Utilities for PINNs
License-File: LICENSE
Requires-Python: >=3.12
Requires-Dist: matplotlib>=3.10.1
Requires-Dist: numpy>=2.2.4
Requires-Dist: torch>=2.6.0
